speedtable/speedtable.cpython-313-darwin.so
speedtable/__init__.py
speedtable/speedtable.pyi
speedtable/speedtable.c
speedtable-1.0.5.dist-info/RECORD
speedtable-1.0.5.dist-info/WHEEL
speedtable-1.0.5.dist-info/top_level.txt
speedtable-1.0.5.dist-info/METADATA
speedtable-1.0.5.dist-info/licenses/LICENCE
