Metadata-Version: 2.4
Name: speedtable
Version: 1.0.5
Summary: Ultra-fast terminal table renderer written in C
Home-page: https://github.com/canadaluke888/speedtable
Author: Luke Canada
Author-email: canadaluke888@gmail.com
Classifier: Programming Language :: Python :: 3
Classifier: Programming Language :: C
Classifier: Operating System :: OS Independent
Classifier: License :: OSI Approved :: MIT License
Classifier: Intended Audience :: Developers
Classifier: Topic :: Utilities
Requires-Python: >=3.7
License-File: LICENCE
Dynamic: author
Dynamic: author-email
Dynamic: classifier
Dynamic: description
Dynamic: description-content-type
Dynamic: home-page
Dynamic: license-file
Dynamic: requires-python
Dynamic: summary
